setup.cfg
setup.py
npdb/__init__.py
npdb.egg-info/PKG-INFO
npdb.egg-info/SOURCES.txt
npdb.egg-info/dependency_links.txt
npdb.egg-info/not-zip-safe
npdb.egg-info/top_level.txt
npdb/core/__init__.py
npdb/core/config.py
npdb/core/core.py
npdb/core/diskmap.py
npdb/creation/__init__.py
npdb/creation/basic.py
npdb/creation/from_data.py
npdb/creation/matrix.py
npdb/creation/ranges.py
npdb/indexing/__init__.py
npdb/indexing/indexing.py
npdb/linalg/__init__.py
npdb/manipulation/__init__.py
npdb/manipulation/views.py
npdb/math/__init__.py
npdb/random/__init__.py
npdb/sorting/__init__.py
npdb/statistics/__init__.py