Metadata-Version: 1.0
Name: npdb
Version: 0.1
Summary: npdb: NumPy-compatible large, persistent n-dimensional arrays on disk
Home-page: https://github.com/ryanwallace96/npdb
Author: Ryan Wallace
Author-email: ryanwallace@college.harvard.edu
License: MIT
Platform: UNKNOWN
